drange/__init__.py
drange/interval_set.py
drange/py.typed
drange-0.1.0.dist-info/METADATA
drange-0.1.0.dist-info/WHEEL
drange-0.1.0.dist-info/licenses/LICENSE
drange-0.1.0.dist-info/RECORD
