Metadata-Version: 2.4
Name: drange
Version: 0.1.0
Summary: Discrete interval storage and algebra on integers (allowing for positive and negative infinity), stored as coalesced intervals.
Project-URL: Homepage, https://github.com/yourname/drange
Project-URL: Issues, https://github.com/yourname/drange/issues
Author-email: Wesley Oates <wesley.oates@gmail.com>
License: MIT License
License-File: LICENSE
Keywords: coalesced,discrete,infinite,integers,interval,ranges,set
Classifier: Development Status :: 4 - Beta
Classifier: Intended Audience :: Developers
Classifier: License :: OSI Approved :: MIT License
Classifier: Programming Language :: Python :: 3
Classifier: Programming Language :: Python :: 3 :: Only
Classifier: Programming Language :: Python :: 3.9
Classifier: Programming Language :: Python :: 3.10
Classifier: Programming Language :: Python :: 3.11
Classifier: Programming Language :: Python :: 3.12
Classifier: Typing :: Typed
Requires-Python: >=3.9
